toilmoresdk/__init__.py
toilmoresdk/api_config.py
toilmoresdk/constants.py
toilmoresdk/entry_point.py
toilmoresdk/http_requester.py
toilmoresdk/image_codecs.py
toilmoresdk/isobmff.py
toilmoresdk/stream_helpers.py
toilmoresdk/submit_machine.py
toilmoresdk/types.py
toilmoresdk/version.py
toilmoresdk/environment/__init__.py
toilmoresdk/environment/logging.py
toilmoresdk/json_schemas/adjuster-schema.json
toilmoresdk/tests/__init__.py
toilmoresdk/tests/proxy_to_dev.py
toilmoresdk/tests/test_faults.py
toilmoresdk/tests/test_no_faults.py
toilmore_sdk-0.2.7.dist-info/LICENSE
toilmore_sdk-0.2.7.dist-info/METADATA
toilmore_sdk-0.2.7.dist-info/WHEEL
toilmore_sdk-0.2.7.dist-info/entry_points.txt
toilmore_sdk-0.2.7.dist-info/top_level.txt
toilmore_sdk-0.2.7.dist-info/RECORD
