Metadata-Version: 2.1
Name: toilmore-sdk
Version: 0.2.7
Summary: The Toilmore API SDK provides Python APIs to optimize and process images.
Home-page: https://pixellena.com/
Author: ShimmerCat
Author-email: ops@pixellena.com
License: ISC License
Keywords: image-optimization,image-processing,sdk,shimmercat,pixellena,tilemore,python
Platform: UNKNOWN
Classifier: Intended Audience :: Developers
Classifier: Natural Language :: English
Classifier: Operating System :: OS Independent
Classifier: Programming Language :: Python :: 3.7
Classifier: Programming Language :: Python :: 3.8
Classifier: Programming Language :: Python :: Implementation :: PyPy
Classifier: Topic :: Software Development :: Libraries :: Python Modules
Requires-Dist: aiohttp-retry (==2.1)
Requires-Dist: aiohttp (==3.7.3)
Requires-Dist: asyncfile (==1.0.0)
Requires-Dist: certifi (==2020.12.5)
Requires-Dist: jsonschema (==3.2.0)
Requires-Dist: mypy (==0.790)
